{"gameDetails":{"round":49,"maxRounds":400,"mapWidth":16,"mapHeight":8,"roundIncomeEnergy":5,"buildingPrices":{"ENERGY":20,"TESLA":100,"DEFENSE":30,"ATTACK":30},"buildingsStats":{"ENERGY":{"health":5,"constructionTime":1,"price":20,"weaponDamage":0,"weaponSpeed":0,"weaponCooldownPeriod":0,"energyGeneratedPerTurn":3,"destroyMultiplier":1,"constructionScore":3},"TESLA":{"health":5,"constructionTime":10,"price":100,"weaponDamage":20,"weaponSpeed":0,"weaponCooldownPeriod":10,"energyGeneratedPerTurn":0,"destroyMultiplier":10,"constructionScore":20},"DEFENSE":{"health":20,"constructionTime":3,"price":30,"weaponDamage":0,"weaponSpeed":0,"weaponCooldownPeriod":0,"energyGeneratedPerTurn":0,"destroyMultiplier":1,"constructionScore":10},"ATTACK":{"health":5,"constructionTime":1,"price":30,"weaponDamage":5,"weaponSpeed":2,"weaponCooldownPeriod":3,"energyGeneratedPerTurn":0,"destroyMultiplier":1,"constructionScore":4}},"ironCurtainStats":{"activeRounds":6,"resetPeriod":30,"price":100,"constructionScore":20}},"players":[{"playerType":"A","energy":28,"health":5,"hitsTaken":19,"score":1658,"ironCurtainAvailable":true,"activeIronCurtainLifetime":-19,"isIronCurtainActive":false},{"playerType":"B","energy":44,"health":70,"hitsTaken":6,"score":3124,"ironCurtainAvailable":true,"activeIronCurtainLifetime":-19,"isIronCurtainActive":false}],"gameMap":[[{"x":0,"y":0,"buildings":[{"health":5,"constructionTimeLeft":-38,"price":20,"weaponDamage":0,"weaponSpeed":0,"weaponCooldownTimeLeft":0,"weaponCooldownPeriod":0,"destroyMultiplier":1,"constructionScore":3,"energyGeneratedPerTurn":3,"maxRange":0,"buildingType":"ENERGY","energyPerShot":0,"x":0,"y":0,"playerType":"A"}],"missiles":[],"cellOwner":"A"},{"x":1,"y":0,"buildings":[],"missiles":[],"cellOwner":"A"},{"x":2,"y":0,"buildings":[],"missiles":[{"damage":5,"speed":2,"id":"83a03b5e-92a0-4ca2-a01a-d3ad4fc990e0","x":2,"y":0,"playerType":"B"}],"cellOwner":"A"},{"x":3,"y":0,"buildings":[],"missiles":[],"cellOwner":"A"},{"x":4,"y":0,"buildings":[],"missiles":[],"cellOwner":"A"},{"x":5,"y":0,"buildings":[],"missiles":[{"damage":5,"speed":2,"id":"6367babe-3fa4-4ea8-8e95-53942f6808d7","x":5,"y":0,"playerType":"B"}],"cellOwner":"A"},{"x":6,"y":0,"buildings":[],"missiles":[],"cellOwner":"A"},{"x":7,"y":0,"buildings":[{"health":10,"constructionTimeLeft":-1,"price":30,"weaponDamage":0,"weaponSpeed":0,"weaponCooldownTimeLeft":0,"weaponCooldownPeriod":0,"destroyMultiplier":1,"constructionScore":10,"energyGeneratedPerTurn":0,"maxRange":0,"buildingType":"DEFENSE","energyPerShot":0,"x":7,"y":0,"playerType":"A"}],"missiles":[],"cellOwner":"A"},{"x":8,"y":0,"buildings":[{"health":20,"constructionTimeLeft":-14,"price":30,"weaponDamage":0,"weaponSpeed":0,"weaponCooldownTimeLeft":0,"weaponCooldownPeriod":0,"destroyMultiplier":1,"constructionScore":10,"energyGeneratedPerTurn":0,"maxRange":0,"buildingType":"DEFENSE","energyPerShot":0,"x":8,"y":0,"playerType":"B"}],"missiles":[],"cellOwner":"B"},{"x":9,"y":0,"buildings":[],"missiles":[],"cellOwner":"B"},{"x":10,"y":0,"buildings":[{"health":5,"constructionTimeLeft":-2,"price":30,"weaponDamage":5,"weaponSpeed":2,"weaponCooldownTimeLeft":2,"weaponCooldownPeriod":3,"destroyMultiplier":1,"constructionScore":4,"energyGeneratedPerTurn":0,"maxRange":0,"buildingType":"ATTACK","energyPerShot":0,"x":10,"y":0,"playerType":"B"}],"missiles":[{"damage":5,"speed":2,"id":"dc9cb249-9608-4db5-ae4c-454f38c4e4ca","x":10,"y":0,"playerType":"B"}],"cellOwner":"B"},{"x":11,"y":0,"buildings":[{"health":5,"constructionTimeLeft":-3,"price":30,"weaponDamage":5,"weaponSpeed":2,"weaponCooldownTimeLeft":1,"weaponCooldownPeriod":3,"destroyMultiplier":1,"constructionScore":4,"energyGeneratedPerTurn":0,"maxRange":0,"buildingType":"ATTACK","energyPerShot":0,"x":11,"y":0,"playerType":"B"}],"missiles":[],"cellOwner":"B"},{"x":12,"y":0,"buildings":[{"health":5,"constructionTimeLeft":-9,"price":30,"weaponDamage":5,"weaponSpeed":2,"weaponCooldownTimeLeft":3,"weaponCooldownPeriod":3,"destroyMultiplier":1,"constructionScore":4,"energyGeneratedPerTurn":0,"maxRange":0,"buildingType":"ATTACK","energyPerShot":0,"x":12,"y":0,"playerType":"B"}],"missiles":[],"cellOwner":"B"},{"x":13,"y":0,"buildings":[{"health":5,"constructionTimeLeft":-15,"price":30,"weaponDamage":5,"weaponSpeed":2,"weaponCooldownTimeLeft":1,"weaponCooldownPeriod":3,"destroyMultiplier":1,"constructionScore":4,"energyGeneratedPerTurn":0,"maxRange":0,"buildingType":"ATTACK","energyPerShot":0,"x":13,"y":0,"playerType":"B"}],"missiles":[],"cellOwner":"B"},{"x":14,"y":0,"buildings":[],"missiles":[],"cellOwner":"B"},{"x":15,"y":0,"buildings":[{"health":5,"constructionTimeLeft":-13,"price":20,"weaponDamage":0,"weaponSpeed":0,"weaponCooldownTimeLeft":0,"weaponCooldownPeriod":0,"destroyMultiplier":1,"constructionScore":3,"energyGeneratedPerTurn":3,"maxRange":0,"buildingType":"ENERGY","energyPerShot":0,"x":15,"y":0,"playerType":"B"}],"missiles":[],"cellOwner":"B"}],[{"x":0,"y":1,"buildings":[],"missiles":[],"cellOwner":"A"},{"x":1,"y":1,"buildings":[],"missiles":[{"damage":5,"speed":2,"id":"5aa631c1-a16a-447c-8a7d-d52d8b3971ad","x":1,"y":1,"playerType":"B"}],"cellOwner":"A"},{"x":2,"y":1,"buildings":[],"missiles":[],"cellOwner":"A"},{"x":3,"y":1,"buildings":[],"missiles":[],"cellOwner":"A"},{"x":4,"y":1,"buildings":[],"missiles":[],"cellOwner":"A"},{"x":5,"y":1,"buildings":[],"missiles":[],"cellOwner":"A"},{"x":6,"y":1,"buildings":[],"missiles":[],"cellOwner":"A"},{"x":7,"y":1,"buildings":[{"health":10,"constructionTimeLeft":-3,"price":30,"weaponDamage":0,"weaponSpeed":0,"weaponCooldownTimeLeft":0,"weaponCooldownPeriod":0,"destroyMultiplier":1,"constructionScore":10,"energyGeneratedPerTurn":0,"maxRange":0,"buildingType":"DEFENSE","energyPerShot":0,"x":7,"y":1,"playerType":"A"}],"missiles":[],"cellOwner":"A"},{"x":8,"y":1,"buildings":[],"missiles":[],"cellOwner":"B"},{"x":9,"y":1,"buildings":[],"missiles":[{"damage":5,"speed":2,"id":"f3860582-515d-4b4d-bc39-78409ebd2f3d","x":9,"y":1,"playerType":"B"}],"cellOwner":"B"},{"x":10,"y":1,"buildings":[],"missiles":[],"cellOwner":"B"},{"x":11,"y":1,"buildings":[{"health":5,"constructionTimeLeft":-23,"price":30,"weaponDamage":5,"weaponSpeed":2,"weaponCooldownTimeLeft":1,"weaponCooldownPeriod":3,"destroyMultiplier":1,"constructionScore":4,"energyGeneratedPerTurn":0,"maxRange":0,"buildingType":"ATTACK","energyPerShot":0,"x":11,"y":1,"playerType":"B"}],"missiles":[],"cellOwner":"B"},{"x":12,"y":1,"buildings":[{"health":5,"constructionTimeLeft":-24,"price":30,"weaponDamage":5,"weaponSpeed":2,"weaponCooldownTimeLeft":0,"weaponCooldownPeriod":3,"destroyMultiplier":1,"constructionScore":4,"energyGeneratedPerTurn":0,"maxRange":0,"buildingType":"ATTACK","energyPerShot":0,"x":12,"y":1,"playerType":"B"}],"missiles":[],"cellOwner":"B"},{"x":13,"y":1,"buildings":[{"health":5,"constructionTimeLeft":-26,"price":30,"weaponDamage":5,"weaponSpeed":2,"weaponCooldownTimeLeft":2,"weaponCooldownPeriod":3,"destroyMultiplier":1,"constructionScore":4,"energyGeneratedPerTurn":0,"maxRange":0,"buildingType":"ATTACK","energyPerShot":0,"x":13,"y":1,"playerType":"B"}],"missiles":[],"cellOwner":"B"},{"x":14,"y":1,"buildings":[],"missiles":[],"cellOwner":"B"},{"x":15,"y":1,"buildings":[{"health":5,"constructionTimeLeft":-41,"price":20,"weaponDamage":0,"weaponSpeed":0,"weaponCooldownTimeLeft":0,"weaponCooldownPeriod":0,"destroyMultiplier":1,"constructionScore":3,"energyGeneratedPerTurn":3,"maxRange":0,"buildingType":"ENERGY","energyPerShot":0,"x":15,"y":1,"playerType":"B"}],"missiles":[],"cellOwner":"B"}],[{"x":0,"y":2,"buildings":[],"missiles":[],"cellOwner":"A"},{"x":1,"y":2,"buildings":[],"missiles":[],"cellOwner":"A"},{"x":2,"y":2,"buildings":[],"missiles":[],"cellOwner":"A"},{"x":3,"y":2,"buildings":[],"missiles":[],"cellOwner":"A"},{"x":4,"y":2,"buildings":[],"missiles":[],"cellOwner":"A"},{"x":5,"y":2,"buildings":[],"missiles":[],"cellOwner":"A"},{"x":6,"y":2,"buildings":[],"missiles":[],"cellOwner":"A"},{"x":7,"y":2,"buildings":[{"health":5,"constructionTimeLeft":-6,"price":30,"weaponDamage":0,"weaponSpeed":0,"weaponCooldownTimeLeft":0,"weaponCooldownPeriod":0,"destroyMultiplier":1,"constructionScore":10,"energyGeneratedPerTurn":0,"maxRange":0,"buildingType":"DEFENSE","energyPerShot":0,"x":7,"y":2,"playerType":"A"}],"missiles":[],"cellOwner":"A"},{"x":8,"y":2,"buildings":[],"missiles":[],"cellOwner":"B"},{"x":9,"y":2,"buildings":[],"missiles":[],"cellOwner":"B"},{"x":10,"y":2,"buildings":[],"missiles":[],"cellOwner":"B"},{"x":11,"y":2,"buildings":[],"missiles":[{"damage":5,"speed":2,"id":"464fccc9-6b4b-4a2a-8668-95287ae20202","x":11,"y":2,"playerType":"B"}],"cellOwner":"B"},{"x":12,"y":2,"buildings":[{"health":5,"constructionTimeLeft":-31,"price":30,"weaponDamage":5,"weaponSpeed":2,"weaponCooldownTimeLeft":1,"weaponCooldownPeriod":3,"destroyMultiplier":1,"constructionScore":4,"energyGeneratedPerTurn":0,"maxRange":0,"buildingType":"ATTACK","energyPerShot":0,"x":12,"y":2,"playerType":"B"}],"missiles":[],"cellOwner":"B"},{"x":13,"y":2,"buildings":[{"health":5,"constructionTimeLeft":-33,"price":30,"weaponDamage":5,"weaponSpeed":2,"weaponCooldownTimeLeft":3,"weaponCooldownPeriod":3,"destroyMultiplier":1,"constructionScore":4,"energyGeneratedPerTurn":0,"maxRange":0,"buildingType":"ATTACK","energyPerShot":0,"x":13,"y":2,"playerType":"B"}],"missiles":[],"cellOwner":"B"},{"x":14,"y":2,"buildings":[{"health":5,"constructionTimeLeft":-34,"price":20,"weaponDamage":0,"weaponSpeed":0,"weaponCooldownTimeLeft":0,"weaponCooldownPeriod":0,"destroyMultiplier":1,"constructionScore":3,"energyGeneratedPerTurn":3,"maxRange":0,"buildingType":"ENERGY","energyPerShot":0,"x":14,"y":2,"playerType":"B"}],"missiles":[],"cellOwner":"B"},{"x":15,"y":2,"buildings":[{"health":5,"constructionTimeLeft":-45,"price":20,"weaponDamage":0,"weaponSpeed":0,"weaponCooldownTimeLeft":0,"weaponCooldownPeriod":0,"destroyMultiplier":1,"constructionScore":3,"energyGeneratedPerTurn":3,"maxRange":0,"buildingType":"ENERGY","energyPerShot":0,"x":15,"y":2,"playerType":"B"}],"missiles":[],"cellOwner":"B"}],[{"x":0,"y":3,"buildings":[],"missiles":[],"cellOwner":"A"},{"x":1,"y":3,"buildings":[],"missiles":[],"cellOwner":"A"},{"x":2,"y":3,"buildings":[],"missiles":[],"cellOwner":"A"},{"x":3,"y":3,"buildings":[],"missiles":[],"cellOwner":"A"},{"x":4,"y":3,"buildings":[],"missiles":[],"cellOwner":"A"},{"x":5,"y":3,"buildings":[],"missiles":[],"cellOwner":"A"},{"x":6,"y":3,"buildings":[],"missiles":[],"cellOwner":"A"},{"x":7,"y":3,"buildings":[{"health":5,"constructionTimeLeft":-5,"price":30,"weaponDamage":0,"weaponSpeed":0,"weaponCooldownTimeLeft":0,"weaponCooldownPeriod":0,"destroyMultiplier":1,"constructionScore":10,"energyGeneratedPerTurn":0,"maxRange":0,"buildingType":"DEFENSE","energyPerShot":0,"x":7,"y":3,"playerType":"A"}],"missiles":[],"cellOwner":"A"},{"x":8,"y":3,"buildings":[],"missiles":[],"cellOwner":"B"},{"x":9,"y":3,"buildings":[],"missiles":[],"cellOwner":"B"},{"x":10,"y":3,"buildings":[],"missiles":[],"cellOwner":"B"},{"x":11,"y":3,"buildings":[{"health":5,"constructionTimeLeft":-7,"price":30,"weaponDamage":5,"weaponSpeed":2,"weaponCooldownTimeLeft":1,"weaponCooldownPeriod":3,"destroyMultiplier":1,"constructionScore":4,"energyGeneratedPerTurn":0,"maxRange":0,"buildingType":"ATTACK","energyPerShot":0,"x":11,"y":3,"playerType":"B"}],"missiles":[],"cellOwner":"B"},{"x":12,"y":3,"buildings":[{"health":5,"constructionTimeLeft":-28,"price":30,"weaponDamage":5,"weaponSpeed":2,"weaponCooldownTimeLeft":0,"weaponCooldownPeriod":3,"destroyMultiplier":1,"constructionScore":4,"energyGeneratedPerTurn":0,"maxRange":0,"buildingType":"ATTACK","energyPerShot":0,"x":12,"y":3,"playerType":"B"}],"missiles":[],"cellOwner":"B"},{"x":13,"y":3,"buildings":[{"health":5,"constructionTimeLeft":-32,"price":30,"weaponDamage":5,"weaponSpeed":2,"weaponCooldownTimeLeft":0,"weaponCooldownPeriod":3,"destroyMultiplier":1,"constructionScore":4,"energyGeneratedPerTurn":0,"maxRange":0,"buildingType":"ATTACK","energyPerShot":0,"x":13,"y":3,"playerType":"B"}],"missiles":[],"cellOwner":"B"},{"x":14,"y":3,"buildings":[],"missiles":[],"cellOwner":"B"},{"x":15,"y":3,"buildings":[{"health":5,"constructionTimeLeft":-36,"price":20,"weaponDamage":0,"weaponSpeed":0,"weaponCooldownTimeLeft":0,"weaponCooldownPeriod":0,"destroyMultiplier":1,"constructionScore":3,"energyGeneratedPerTurn":3,"maxRange":0,"buildingType":"ENERGY","energyPerShot":0,"x":15,"y":3,"playerType":"B"}],"missiles":[],"cellOwner":"B"}],[{"x":0,"y":4,"buildings":[{"health":5,"constructionTimeLeft":-41,"price":20,"weaponDamage":0,"weaponSpeed":0,"weaponCooldownTimeLeft":0,"weaponCooldownPeriod":0,"destroyMultiplier":1,"constructionScore":3,"energyGeneratedPerTurn":3,"maxRange":0,"buildingType":"ENERGY","energyPerShot":0,"x":0,"y":4,"playerType":"A"}],"missiles":[],"cellOwner":"A"},{"x":1,"y":4,"buildings":[],"missiles":[],"cellOwner":"A"},{"x":2,"y":4,"buildings":[],"missiles":[],"cellOwner":"A"},{"x":3,"y":4,"buildings":[{"health":5,"constructionTimeLeft":-26,"price":30,"weaponDamage":5,"weaponSpeed":2,"weaponCooldownTimeLeft":2,"weaponCooldownPeriod":3,"destroyMultiplier":1,"constructionScore":4,"energyGeneratedPerTurn":0,"maxRange":0,"buildingType":"ATTACK","energyPerShot":0,"x":3,"y":4,"playerType":"A"}],"missiles":[],"cellOwner":"A"},{"x":4,"y":4,"buildings":[],"missiles":[],"cellOwner":"A"},{"x":5,"y":4,"buildings":[],"missiles":[],"cellOwner":"A"},{"x":6,"y":4,"buildings":[],"missiles":[],"cellOwner":"A"},{"x":7,"y":4,"buildings":[],"missiles":[{"damage":5,"speed":2,"id":"f7d4c1ac-2d08-48f9-8216-7c2ffe52a209","x":7,"y":4,"playerType":"A"}],"cellOwner":"A"},{"x":8,"y":4,"buildings":[{"health":15,"constructionTimeLeft":-3,"price":30,"weaponDamage":0,"weaponSpeed":0,"weaponCooldownTimeLeft":0,"weaponCooldownPeriod":0,"destroyMultiplier":1,"constructionScore":10,"energyGeneratedPerTurn":0,"maxRange":0,"buildingType":"DEFENSE","energyPerShot":0,"x":8,"y":4,"playerType":"B"}],"missiles":[],"cellOwner":"B"},{"x":9,"y":4,"buildings":[],"missiles":[],"cellOwner":"B"},{"x":10,"y":4,"buildings":[],"missiles":[],"cellOwner":"B"},{"x":11,"y":4,"buildings":[],"missiles":[{"damage":5,"speed":2,"id":"47774683-80a2-403d-be21-1b385993141c","x":11,"y":4,"playerType":"B"}],"cellOwner":"B"},{"x":12,"y":4,"buildings":[],"missiles":[],"cellOwner":"B"},{"x":13,"y":4,"buildings":[{"health":5,"constructionTimeLeft":-1,"price":30,"weaponDamage":5,"weaponSpeed":2,"weaponCooldownTimeLeft":3,"weaponCooldownPeriod":3,"destroyMultiplier":1,"constructionScore":4,"energyGeneratedPerTurn":0,"maxRange":0,"buildingType":"ATTACK","energyPerShot":0,"x":13,"y":4,"playerType":"B"}],"missiles":[],"cellOwner":"B"},{"x":14,"y":4,"buildings":[],"missiles":[],"cellOwner":"B"},{"x":15,"y":4,"buildings":[{"health":5,"constructionTimeLeft":0,"price":20,"weaponDamage":0,"weaponSpeed":0,"weaponCooldownTimeLeft":0,"weaponCooldownPeriod":0,"destroyMultiplier":1,"constructionScore":3,"energyGeneratedPerTurn":3,"maxRange":0,"buildingType":"ENERGY","energyPerShot":0,"x":15,"y":4,"playerType":"B"}],"missiles":[{"damage":5,"speed":2,"id":"9b0453c3-3199-4b67-991b-6f93fb800b01","x":15,"y":4,"playerType":"A"}],"cellOwner":"B"}],[{"x":0,"y":5,"buildings":[],"missiles":[{"damage":5,"speed":2,"id":"6966539b-8176-4488-8d8a-290bb53d57dd","x":0,"y":5,"playerType":"B"}],"cellOwner":"A"},{"x":1,"y":5,"buildings":[],"missiles":[{"damage":5,"speed":2,"id":"20968e83-dab2-4324-9cd3-2a5937a79480","x":1,"y":5,"playerType":"B"}],"cellOwner":"A"},{"x":2,"y":5,"buildings":[],"missiles":[],"cellOwner":"A"},{"x":3,"y":5,"buildings":[],"missiles":[],"cellOwner":"A"},{"x":4,"y":5,"buildings":[],"missiles":[],"cellOwner":"A"},{"x":5,"y":5,"buildings":[],"missiles":[],"cellOwner":"A"},{"x":6,"y":5,"buildings":[],"missiles":[],"cellOwner":"A"},{"x":7,"y":5,"buildings":[{"health":20,"constructionTimeLeft":1,"price":30,"weaponDamage":0,"weaponSpeed":0,"weaponCooldownTimeLeft":0,"weaponCooldownPeriod":0,"destroyMultiplier":1,"constructionScore":10,"energyGeneratedPerTurn":0,"maxRange":0,"buildingType":"DEFENSE","energyPerShot":0,"x":7,"y":5,"playerType":"A"}],"missiles":[{"damage":5,"speed":2,"id":"9c1e517f-4ac3-45dc-8438-503e9827c09a","x":7,"y":5,"playerType":"B"}],"cellOwner":"A"},{"x":8,"y":5,"buildings":[],"missiles":[{"damage":5,"speed":2,"id":"60de0ba5-dc26-4c19-998c-f24cb8dae3ee","x":8,"y":5,"playerType":"B"}],"cellOwner":"B"},{"x":9,"y":5,"buildings":[],"missiles":[{"damage":5,"speed":2,"id":"f334ecc1-165f-4db6-a3bd-e0f172df0f11","x":9,"y":5,"playerType":"B"}],"cellOwner":"B"},{"x":10,"y":5,"buildings":[],"missiles":[],"cellOwner":"B"},{"x":11,"y":5,"buildings":[{"health":5,"constructionTimeLeft":-6,"price":30,"weaponDamage":5,"weaponSpeed":2,"weaponCooldownTimeLeft":2,"weaponCooldownPeriod":3,"destroyMultiplier":1,"constructionScore":4,"energyGeneratedPerTurn":0,"maxRange":0,"buildingType":"ATTACK","energyPerShot":0,"x":11,"y":5,"playerType":"B"}],"missiles":[],"cellOwner":"B"},{"x":12,"y":5,"buildings":[{"health":5,"constructionTimeLeft":-10,"price":30,"weaponDamage":5,"weaponSpeed":2,"weaponCooldownTimeLeft":2,"weaponCooldownPeriod":3,"destroyMultiplier":1,"constructionScore":4,"energyGeneratedPerTurn":0,"maxRange":0,"buildingType":"ATTACK","energyPerShot":0,"x":12,"y":5,"playerType":"B"}],"missiles":[],"cellOwner":"B"},{"x":13,"y":5,"buildings":[{"health":5,"constructionTimeLeft":-30,"price":30,"weaponDamage":5,"weaponSpeed":2,"weaponCooldownTimeLeft":2,"weaponCooldownPeriod":3,"destroyMultiplier":1,"constructionScore":4,"energyGeneratedPerTurn":0,"maxRange":0,"buildingType":"ATTACK","energyPerShot":0,"x":13,"y":5,"playerType":"B"}],"missiles":[],"cellOwner":"B"},{"x":14,"y":5,"buildings":[],"missiles":[],"cellOwner":"B"},{"x":15,"y":5,"buildings":[{"health":5,"constructionTimeLeft":-43,"price":20,"weaponDamage":0,"weaponSpeed":0,"weaponCooldownTimeLeft":0,"weaponCooldownPeriod":0,"destroyMultiplier":1,"constructionScore":3,"energyGeneratedPerTurn":3,"maxRange":0,"buildingType":"ENERGY","energyPerShot":0,"x":15,"y":5,"playerType":"B"}],"missiles":[],"cellOwner":"B"}],[{"x":0,"y":6,"buildings":[],"missiles":[],"cellOwner":"A"},{"x":1,"y":6,"buildings":[],"missiles":[],"cellOwner":"A"},{"x":2,"y":6,"buildings":[],"missiles":[],"cellOwner":"A"},{"x":3,"y":6,"buildings":[],"missiles":[],"cellOwner":"A"},{"x":4,"y":6,"buildings":[],"missiles":[],"cellOwner":"A"},{"x":5,"y":6,"buildings":[],"missiles":[],"cellOwner":"A"},{"x":6,"y":6,"buildings":[],"missiles":[],"cellOwner":"A"},{"x":7,"y":6,"buildings":[],"missiles":[{"damage":5,"speed":2,"id":"e3dc4e85-62f7-48dd-a83f-6f6a987797ef","x":7,"y":6,"playerType":"B"}],"cellOwner":"A"},{"x":8,"y":6,"buildings":[],"missiles":[{"damage":5,"speed":2,"id":"b8dc7180-b05c-4718-a170-6b1455e8c61b","x":8,"y":6,"playerType":"B"}],"cellOwner":"B"},{"x":9,"y":6,"buildings":[],"missiles":[],"cellOwner":"B"},{"x":10,"y":6,"buildings":[],"missiles":[],"cellOwner":"B"},{"x":11,"y":6,"buildings":[],"missiles":[],"cellOwner":"B"},{"x":12,"y":6,"buildings":[{"health":5,"constructionTimeLeft":-14,"price":30,"weaponDamage":5,"weaponSpeed":2,"weaponCooldownTimeLeft":2,"weaponCooldownPeriod":3,"destroyMultiplier":1,"constructionScore":4,"energyGeneratedPerTurn":0,"maxRange":0,"buildingType":"ATTACK","energyPerShot":0,"x":12,"y":6,"playerType":"B"}],"missiles":[],"cellOwner":"B"},{"x":13,"y":6,"buildings":[{"health":5,"constructionTimeLeft":-39,"price":30,"weaponDamage":5,"weaponSpeed":2,"weaponCooldownTimeLeft":1,"weaponCooldownPeriod":3,"destroyMultiplier":1,"constructionScore":4,"energyGeneratedPerTurn":0,"maxRange":0,"buildingType":"ATTACK","energyPerShot":0,"x":13,"y":6,"playerType":"B"}],"missiles":[],"cellOwner":"B"},{"x":14,"y":6,"buildings":[],"missiles":[],"cellOwner":"B"},{"x":15,"y":6,"buildings":[{"health":5,"constructionTimeLeft":-37,"price":20,"weaponDamage":0,"weaponSpeed":0,"weaponCooldownTimeLeft":0,"weaponCooldownPeriod":0,"destroyMultiplier":1,"constructionScore":3,"energyGeneratedPerTurn":3,"maxRange":0,"buildingType":"ENERGY","energyPerShot":0,"x":15,"y":6,"playerType":"B"}],"missiles":[],"cellOwner":"B"}],[{"x":0,"y":7,"buildings":[],"missiles":[],"cellOwner":"A"},{"x":1,"y":7,"buildings":[],"missiles":[],"cellOwner":"A"},{"x":2,"y":7,"buildings":[],"missiles":[],"cellOwner":"A"},{"x":3,"y":7,"buildings":[],"missiles":[],"cellOwner":"A"},{"x":4,"y":7,"buildings":[],"missiles":[],"cellOwner":"A"},{"x":5,"y":7,"buildings":[],"missiles":[{"damage":5,"speed":2,"id":"67e198d0-9ed4-47a1-9262-d86194c69259","x":5,"y":7,"playerType":"B"}],"cellOwner":"A"},{"x":6,"y":7,"buildings":[],"missiles":[],"cellOwner":"A"},{"x":7,"y":7,"buildings":[],"missiles":[],"cellOwner":"A"},{"x":8,"y":7,"buildings":[],"missiles":[],"cellOwner":"B"},{"x":9,"y":7,"buildings":[],"missiles":[],"cellOwner":"B"},{"x":10,"y":7,"buildings":[],"missiles":[],"cellOwner":"B"},{"x":11,"y":7,"buildings":[],"missiles":[],"cellOwner":"B"},{"x":12,"y":7,"buildings":[],"missiles":[],"cellOwner":"B"},{"x":13,"y":7,"buildings":[{"health":5,"constructionTimeLeft":-8,"price":30,"weaponDamage":5,"weaponSpeed":2,"weaponCooldownTimeLeft":0,"weaponCooldownPeriod":3,"destroyMultiplier":1,"constructionScore":4,"energyGeneratedPerTurn":0,"maxRange":0,"buildingType":"ATTACK","energyPerShot":0,"x":13,"y":7,"playerType":"B"}],"missiles":[],"cellOwner":"B"},{"x":14,"y":7,"buildings":[],"missiles":[],"cellOwner":"B"},{"x":15,"y":7,"buildings":[{"health":5,"constructionTimeLeft":-12,"price":20,"weaponDamage":0,"weaponSpeed":0,"weaponCooldownTimeLeft":0,"weaponCooldownPeriod":0,"destroyMultiplier":1,"constructionScore":3,"energyGeneratedPerTurn":3,"maxRange":0,"buildingType":"ENERGY","energyPerShot":0,"x":15,"y":7,"playerType":"B"}],"missiles":[],"cellOwner":"B"}]],"teslaHitList":[],"ironCurtainHitList":[]}